<?xml version="1.0" encoding="utf-8"?>
<Dictionaries>
  <Dictionary>
    <DictionaryName>war-2022-07-03</DictionaryName>
    <Word>
      <Native>fatigue</Native>
      <Translation>n физ. усталость (металлов)</Translation>
    </Word>
    <Word>
      <Native>discomfit</Native>
      <Translation>расстраивать, разрушать или срывать (планы, намерения)</Translation>
    </Word>
    <Word>
      <Native>decease</Native>
      <Translation>_юр. скончаться</Translation>
    </Word>
    <Word>
      <Native>deceive</Native>
      <Translation>сознательно вводить в заблуждение</Translation>
    </Word>
    <Word>
      <Native>bolster</Native>
      <Translation>буфер валик (под подушку)</Translation>
    </Word>
    <Word>
      <Native>backdrop</Native>
      <Translation>декорации, художественное оформление</Translation>
    </Word>
    <Word>
      <Native>decisive</Native>
      <Translation>убедительныйокончательный,  решающий</Translation>
    </Word>
    <Word>
      <Native>rumble</Native>
      <Translation>громыхание,  грохот гул</Translation>
    </Word>
    <Word>
      <Native>misery</Native>
      <Translation>страдание; горе; мучение</Translation>
    </Word>
    <Word>
      <Native>ambient</Native>
      <Translation>_книж. окружающий,  внешний омывающий</Translation>
    </Word>
    <Word>
      <Native>susceptible</Native>
      <Translation>восприимчивый,  чувствительный</Translation>
    </Word>
    <Word>
      <Native>ally</Native>
      <Translation>союзник</Translation>
    </Word>
    <Word>
      <Native>distract</Native>
      <Translation>отвлекать, уводить в сторону; рассеивать</Translation>
    </Word>
    <Word>
      <Native>crucial</Native>
      <Translation>решающий; ключевой критический</Translation>
    </Word>
    <Word>
      <Native>embark</Native>
      <Translation>грузить на корабль; принимать на борт</Translation>
    </Word>
    <Word>
      <Native>desensitize</Native>
      <Translation>возвращать в нормальное (психическое) состояние;</Translation>
    </Word>
    <Word>
      <Native>cope</Native>
      <Translation>справиться, совладеть  покров</Translation>
    </Word>
    <Word>
      <Native>wretch</Native>
      <Translation>несчастный,  жалкий человек бессовестный тип</Translation>
    </Word>
    <Word>
      <Native>vowel</Native>
      <Translation>гласный (звук)</Translation>
    </Word>
    <Word>
      <Native>bleed</Native>
      <Translation>кровоточить; истекать кровью;</Translation>
    </Word>
    <Word>
      <Native>shell</Native>
      <Translation>снаряд (артиллерийский), оболочка,  скорлупа,</Translation>
    </Word>
    <Word>
      <Native>refinery</Native>
      <Translation>нефтеперегонный завод</Translation>
    </Word>
    <Word>
      <Native>verge</Native>
      <Translation>край бордюр, кайма опушка</Translation>
    </Word>
    <Word>
      <Native>retaliatory</Native>
      <Translation>ответный (удар)</Translation>
    </Word>
    <Word>
      <Native>reckless</Native>
      <Translation>безумный безрассудный, опрометчивый</Translation>
    </Word>
    <Word>
      <Native>intact</Native>
      <Translation>а неповрежденный,  целый</Translation>
    </Word>
    <Word>
      <Native>spawn</Native>
      <Translation>плодить, порождать, создавать</Translation>
    </Word>
    <Word>
      <Native>layman</Native>
      <Translation>непрофессионал, любитель</Translation>
    </Word>
    <Word>
      <Native>pretext</Native>
      <Translation>предлог,  отговорка</Translation>
    </Word>
    <Word>
      <Native>trump</Native>
      <Translation>козырь,  козырная карта</Translation>
    </Word>
    <Word>
      <Native>backer</Native>
      <Translation>ставящий на игрока</Translation>
    </Word>
    <Word>
      <Native>inexplicable</Native>
      <Translation>не объяснимый,</Translation>
    </Word>
    <Word>
      <Native>harass</Native>
      <Translation>беспокоить, тревожить  раздражение</Translation>
    </Word>
    <Word>
      <Native>ground</Native>
      <Translation>земля, грунт,  молотый</Translation>
    </Word>
    <Word>
      <Native>trauma</Native>
      <Translation>_мед. травма</Translation>
    </Word>
  </Dictionary>
</Dictionaries>